{
  "db_name": "PostgreSQL",
  "query": "SELECT * FROM groups WHERE id = $1",
  "describe": {
    "columns": [
      {
        "ordinal": 0,
        "name": "id",
        "type_info": "Varchar"
      },
      {
        "ordinal": 1,
        "name": "name",
        "type_info": "Varchar"
      }
    ],
    "parameters": {
      "Left": [
        "Text"
      ]
    },
    "nullable": [
      false,
      false
    ]
  },
  "hash": "faffa565a683f0db53199d7b03cd27d4fd54f99ea1ddd79db83001262fb8122c"
}
